streamlit_advanced_audio/__init__.py
streamlit_advanced_audio/frontend/build/asset-manifest.json
streamlit_advanced_audio/frontend/build/bootstrap.min.css
streamlit_advanced_audio/frontend/build/index.html
streamlit_advanced_audio/frontend/build/static/css/main.14ad8115.css
streamlit_advanced_audio/frontend/build/static/css/main.14ad8115.css.map
streamlit_advanced_audio/frontend/build/static/js/main.d08c86af.js
streamlit_advanced_audio/frontend/build/static/js/main.d08c86af.js.LICENSE.txt
streamlit_advanced_audio/frontend/build/static/js/main.d08c86af.js.map
streamlit_advanced_audio-0.1.2.dist-info/licenses/LICENSE
streamlit_advanced_audio-0.1.2.dist-info/METADATA
streamlit_advanced_audio-0.1.2.dist-info/WHEEL
streamlit_advanced_audio-0.1.2.dist-info/top_level.txt
streamlit_advanced_audio-0.1.2.dist-info/RECORD
