Metadata-Version: 2.4
Name: streamlit-advanced-audio
Version: 0.1.2
Summary: Advanced audio player component for Streamlit with waveform visualization and region selection
Home-page: https://github.com/keli-wen/streamlit-advanced-audio
Author: Keli Wen
Author-email: pkuwkl@gmail.com
Classifier: Development Status :: 4 - Beta
Classifier: Environment :: Web Environment
Classifier: Intended Audience :: Developers
Classifier: License :: OSI Approved :: MIT License
Classifier: Operating System :: OS Independent
Classifier: Programming Language :: Python :: 3
Classifier: Programming Language :: Python :: 3.7
Classifier: Programming Language :: Python :: 3.8
Classifier: Programming Language :: Python :: 3.9
Classifier: Programming Language :: Python :: 3.10
Classifier: Programming Language :: Python :: 3.11
Classifier: Topic :: Software Development :: Libraries :: Python Modules
Requires-Python: >=3.7
License-File: LICENSE
Requires-Dist: streamlit>=0.63
Requires-Dist: numpy
Requires-Dist: pandas
Requires-Dist: requests
Requires-Dist: soundfile
Provides-Extra: dev
Requires-Dist: wheel; extra == "dev"
Requires-Dist: pytest==7.4.0; extra == "dev"
Requires-Dist: playwright==1.48.0; extra == "dev"
Requires-Dist: requests==2.31.0; extra == "dev"
Requires-Dist: pytest-playwright-snapshot==1.0; extra == "dev"
Requires-Dist: pytest-rerunfailures==12.0; extra == "dev"
Dynamic: author
Dynamic: author-email
Dynamic: classifier
Dynamic: description
Dynamic: description-content-type
Dynamic: home-page
Dynamic: license-file
Dynamic: provides-extra
Dynamic: requires-dist
Dynamic: requires-python
Dynamic: summary
